[
  {
    "content": "AJ1: Backend routers_am.py (templates CRUD + duplicate, submissions, coverage, PDF, public endpoints) + register in server.py",
    "status": "in_progress"
  },
  {
    "content": "AJ2a: Shared AmChecklistForm component (tri-state, remarks gating, metadata)",
    "status": "pending"
  },
  {
    "content": "AJ2b: Public /am-checklist page + Login page AM button",
    "status": "pending"
  },
  {
    "content": "AJ2c: In-app /am-checklists module (coverage board, templates admin, history) + sidebar + routes",
    "status": "pending"
  },
  {
    "content": "AJ2d: MachineDrawer AM Checklist tab (history + filters + PDF)",
    "status": "pending"
  },
  {
    "content": "AJ3: Seed representative demo AM template (idempotent)",
    "status": "pending"
  },
  {
    "content": "AJ5: Testing agent (both) + fixes",
    "status": "pending"
  }
]